fronty/__init__.py
fronty/cli.py
fronty/css/__init__.py
fronty/html/__init__.py
fronty/html/widgets.py
fronty/js/__init__.py
fronty/middlewares/__init__.py
fronty-0.0.7.dist-info/METADATA
fronty-0.0.7.dist-info/WHEEL
fronty-0.0.7.dist-info/entry_points.txt
fronty-0.0.7.dist-info/licenses/LICENSE
fronty-0.0.7.dist-info/RECORD
