Metadata-Version: 2.1
Name: fronty
Version: 0.0.7
Summary: A frontend web framework
Project-URL: Homepage, https://github.com/Almas-Ali/fronty
Project-URL: Documentation, https://github.com/Almas-Ali/fronty#readme
Project-URL: Repository, https://github.com/Almas-Ali/fronty
Project-URL: Bug Tracker, https://github.com/Almas-Ali/fronty/issues
Author-email: "Md. Almas Ali" <almaspr3@gmail.com>
Maintainer-email: "Md. Almas Ali" <almaspr3@gmail.com>
License: MIT License
License-File: LICENSE
Keywords: css,easy,fast,framework,frontend,frontend framework,html,javascript,light,light-weight,lightweight,quick,rapid,simple,web,web framework
Classifier: Development Status :: 3 - Alpha
Classifier: Intended Audience :: Developers
Classifier: License :: OSI Approved :: MIT License
Classifier: Operating System :: OS Independent
Classifier: Programming Language :: Python :: 3
Classifier: Programming Language :: Python :: 3.7
Classifier: Programming Language :: Python :: 3.8
Classifier: Programming Language :: Python :: 3.9
Classifier: Programming Language :: Python :: 3.10
Classifier: Programming Language :: Python :: 3.11
Classifier: Programming Language :: Python :: 3.12
Classifier: Programming Language :: Python :: 3.13
Classifier: Topic :: Internet
Requires-Python: >=3.7
